javalang/__init__.py
javalang/ast.py
javalang/javadoc.py
javalang/parse.py
javalang/parser.py
javalang/tokenizer.py
javalang/tree.py
javalang/util.py
javalang_rgamba-0.12.0.dist-info/LICENSE.txt
javalang_rgamba-0.12.0.dist-info/METADATA
javalang_rgamba-0.12.0.dist-info/WHEEL
javalang_rgamba-0.12.0.dist-info/top_level.txt
javalang_rgamba-0.12.0.dist-info/RECORD
