Metadata-Version: 2.1
Name: javalang-rgamba
Version: 0.12.0
Summary: Pure Python Java parser and tools
Home-page: http://github.com/rgamba/javalang
Author: Chris Thunes
Author-email: cthunes@brewtab.com
License: UNKNOWN
Platform: UNKNOWN
Classifier: Programming Language :: Python
Classifier: Development Status :: 4 - Beta
Classifier: Operating System :: OS Independent
Classifier: License :: OSI Approved :: MIT License
Classifier: Intended Audience :: Developers
Classifier: Topic :: Software Development :: Libraries
Requires-Dist: six
